insightmapper/__init__.py
insightmapper/conditional_analysis.py
insightmapper/dependency_map.py
insightmapper/visualization.py
InsightMapper-0.1.1.dist-info/LICENSE
InsightMapper-0.1.1.dist-info/METADATA
InsightMapper-0.1.1.dist-info/WHEEL
InsightMapper-0.1.1.dist-info/top_level.txt
InsightMapper-0.1.1.dist-info/RECORD
